acetone/__init__.py
acetone/container.py
acetone/dependency.py
acetone/exceptions.py
acetone-0.1.0.dist-info/DESCRIPTION.rst
acetone-0.1.0.dist-info/METADATA
acetone-0.1.0.dist-info/RECORD
acetone-0.1.0.dist-info/WHEEL
acetone-0.1.0.dist-info/metadata.json
acetone-0.1.0.dist-info/top_level.txt
tutorials/tutorial01/__init__.py
tutorials/tutorial01/__main__.py
tutorials/tutorial01/data_sender.py
tutorials/tutorial01/dependencies.py
tutorials/tutorial01/stdout_data_sender.py
tutorials/tutorial01/worker.py
tutorials/tutorial02/__init__.py
tutorials/tutorial02/__main__.py
