Metadata-Version: 2.0
Name: acetone
Version: 0.1.0
Summary: Glue code removal.
Home-page: https://github.com/prokopst/acetone
Author: Stanislav Prokop
Author-email: UNKNOWN
License: MIT
Keywords: dependency injection ioc inversion of control service locator
Platform: UNKNOWN
Classifier: Development Status :: 4 - Beta
Classifier: Intended Audience :: Developers
Classifier: Topic :: Software Development :: Libraries
Classifier: License :: OSI Approved :: MIT License
Classifier: Programming Language :: Python :: 2
Classifier: Programming Language :: Python :: 3
